Metadata-Version: 2.1
Name: stat-g-b-distribution
Version: 0.1.2
Summary: Gaussian distributions
License-File: license.txt
